cartomancy/__init__.py
cartomancy/__main__.py
cartomancy/constants.py
cartomancy/decks.py
cartomancy/query.py
cartomancy-0.1.1.dist-info/licenses/LICENSE
cartomancy-0.1.1.dist-info/METADATA
cartomancy-0.1.1.dist-info/WHEEL
cartomancy-0.1.1.dist-info/entry_points.txt
cartomancy-0.1.1.dist-info/top_level.txt
cartomancy-0.1.1.dist-info/RECORD
