Metadata-Version: 2.4
Name: cartomancy
Version: 0.1.1
Summary: a tarot and minchiate TUI
Author-email: sailorfe <sailorf@proton.me>
License-Expression: MIT
Project-URL: Repository, https://codeberg.org/sailorfe/cartomancy
Keywords: tarot,cartomancy,divination,minchiate,fortunetelling
Classifier: Development Status :: 3 - Alpha
Classifier: Topic :: Games/Entertainment :: Fortune Cookies
Classifier: Programming Language :: Python :: 3
Classifier: Programming Language :: Python :: 3.13
Requires-Python: <4.0,>=3.8
License-File: LICENSE
Dynamic: license-file
